testing/__init__.py
testing/test_data.py
testing/test_mix.py
testing/test_transcript.py
working/__init__.py
working/data.py
working/mix.py
working/transcript.py
ytube_data_and_transcript-0.1.0.dist-info/METADATA
ytube_data_and_transcript-0.1.0.dist-info/WHEEL
ytube_data_and_transcript-0.1.0.dist-info/top_level.txt
ytube_data_and_transcript-0.1.0.dist-info/RECORD
