Metadata-Version: 2.1
Name: ytube-data-and-transcript
Version: 0.1.0
Summary: A python package that utilizes the YouTube Data V3 API to get all transcripts from a given channel/playlist.
Home-page: https://github.com/DevanshL/youtube-channel-transcript-api
Author: Devansh Lingamaneni
Author-email: l.devansh2073@gmail.com
Classifier: Programming Language :: Python :: 3
Classifier: License :: OSI Approved :: MIT License
Classifier: Operating System :: OS Independent
Requires-Python: >=3.6
Requires-Dist: requests>=2.32.3
Requires-Dist: google-api-python-client>=2.138.0
Requires-Dist: youtube-transcript-api>=0.6.2
